sample_stream/__init__.py
sample_stream/__main__.py
sample_stream-0.2.5.dist-info/entry_points.txt
sample_stream-0.2.5.dist-info/LICENSE
sample_stream-0.2.5.dist-info/WHEEL
sample_stream-0.2.5.dist-info/METADATA
sample_stream-0.2.5.dist-info/RECORD
