Metadata-Version: 2.1
Name: sample-stream
Version: 0.2.5
Summary: Filter lines from standard input according to some probability, with a given delay, and for a certain duration.
Home-page: https://github.com/jeroenjanssens/sample-stream
License: MIT
Author: Jeroen Janssens
Author-email: jeroen@jeroenjanssens.com
Requires-Python: >=3.7,<4.0
Classifier: Development Status :: 3 - Alpha
Classifier: Intended Audience :: Developers
Classifier: License :: OSI Approved :: MIT License
Classifier: Operating System :: OS Independent
Classifier: Programming Language :: Python :: 3
Classifier: Programming Language :: Python :: 3.7
Classifier: Programming Language :: Python :: 3.8
Classifier: Programming Language :: Python :: 3.9
Classifier: Topic :: Software Development :: Libraries :: Python Modules
Requires-Dist: importlib_metadata (>=3.7.0,<4.0.0); python_version < "3.8"
Project-URL: Repository, https://github.com/jeroenjanssens/sample-stream
